seismicSignalAnalysis/__init__.py
seismicSignalAnalysis/accDispConvert.py
seismicSignalAnalysis/mainView.py
seismicSignalAnalysis/runProgram.py
seismicSignalAnalysis/spectraCalculation.py
seismicSignalAnalysis-0.1.2.dist-info/DESCRIPTION.rst
seismicSignalAnalysis-0.1.2.dist-info/METADATA
seismicSignalAnalysis-0.1.2.dist-info/RECORD
seismicSignalAnalysis-0.1.2.dist-info/WHEEL
seismicSignalAnalysis-0.1.2.dist-info/metadata.json
seismicSignalAnalysis-0.1.2.dist-info/top_level.txt
