Metadata-Version: 2.0
Name: seismicSignalAnalysis
Version: 0.1.2
Summary: seismic wave analysis
Home-page: https://github.com/Junjun1guo/seismicWaveAnalysis
Author: Junjun Guo
Author-email: guojj_ce@163.com
License: MIT License
Keywords: seismic,signal
Platform: any
